pygameplus/__init__.py
pygameplus/event_loop.py
pygameplus/painter.py
pygameplus/pgputils.py
pygameplus/screen.py
pygameplus/sprite.py
pygameplus/turtle.py
pygameplus/demos/__init__.py
pygameplus/demos/mole.py
pygameplus/demos/penguin.py
pygameplus/demos/space.py
pygameplus/demos/turtle.py
pygameplus/demos/audio/__init__.py
pygameplus/demos/fonts/Freedom.ttf
pygameplus/demos/fonts/__init__.py
pygameplus/demos/img/__init__.py
pygameplus/demos/img/mallet.png
pygameplus/demos/img/mole.png
pygameplus/demos/img/penguin_jump0.png
pygameplus/demos/img/penguin_jump1.png
pygameplus/demos/img/penguin_jump2.png
pygameplus/demos/img/penguin_jumpslide.png
pygameplus/demos/img/penguin_slide.png
pygameplus/demos/img/penguin_stand.png
pygameplus/demos/img/penguin_walk0.png
pygameplus/demos/img/penguin_walk1.png
pygameplus/demos/img/penguin_walk2.png
pygameplus/demos/img/penguin_walk3.png
pygameplus/demos/img/pow.png
pygameplus/demos/img/ship.png
pygameplus/demos/img/ship2.png
pygameplus/demos/img/snow.png
pygameplus/demos/img/snow1.png
pygameplus/demos/img/snow2.png
pygameplus/demos/img/snow3.png
pygameplus/demos/img/snow4.png
pygameplus/demos/img/snow5.png
pygameplus/demos/img/snow6.png
pygameplus/demos/img/snow7.png
pygameplus/demos/img/snow8.png
pygameplus/demos/img/space.jpg
pygameplus/demos/img/ufo.png
pygame_plus-0.0.20.dist-info/LICENSE
pygame_plus-0.0.20.dist-info/METADATA
pygame_plus-0.0.20.dist-info/WHEEL
pygame_plus-0.0.20.dist-info/top_level.txt
pygame_plus-0.0.20.dist-info/RECORD
