Metadata-Version: 2.1
Name: pygame-plus
Version: 0.0.20
Summary: Pygame with some added features for beginners
Author-email: Casey Devet <cjdevet@gmail.com>
License: Copyright 2021 Casey Devet        
Project-URL: Homepage, https://github.com/mrdevet/PygamePlus
Keywords: input,output,io
Classifier: License :: OSI Approved :: MIT License
Classifier: Programming Language :: Python :: 3
Requires-Python: >=3
License-File: LICENSE
Requires-Dist: pygame (>=2.0.0)
